{
  "version": "2.0.0",
  "name": "v2.0.0 - HTML Rendering System",
  "description": "Повна міграція на HTML/CSS систему рендерингу зображень",
  "features": [
    "HTML/CSS рендеринг замість Pillow",
    "5 типів зображень (повний, аварійний, тижневий, матриця, картки)",
    "Playwright рендеринг для високої якості",
    "Українські коментарі у всьому коді",
    "Покращена архітектура та організація коду"
  ],
  "breaking_changes": [
    "Видалена темна тема",
    "Старі Pillow генератори більше не підтримуються",
    "Зміна команд запуску"
  ],
  "migration": [
    "Встановіть Playwright: playwright install chromium",
    "Використовуйте python src/main.py --parse",
    "Перегляньте MIGRATION_GUIDE.md"
  ]
}